dripper/__init__.py
dripper/compat.py
dripper/drippers.py
dripper/exceptions.py
dripper-1.2.dist-info/DESCRIPTION.rst
dripper-1.2.dist-info/METADATA
dripper-1.2.dist-info/RECORD
dripper-1.2.dist-info/WHEEL
dripper-1.2.dist-info/metadata.json
dripper-1.2.dist-info/top_level.txt
