Metadata-Version: 2.0
Name: dripper
Version: 1.2
Summary: Cleaning your messy data.
Home-page: https://github.com/hirokiky/dripper
Author: Hiroki KIYOHARA
Author-email: hirokiky@gmail.com
License: MIT
Keywords: dict data converter cleaning mapping
Platform: UNKNOWN
